{
    "metadataType": "FunctionPage",
    "metadataversion": "3.0",
    "createdBy": "创建人",
    "createdOn": "2025-05-08T14:06:03.3115833+08:00",
    "modifiedBy": "修改人", 
    "modifiedOn": "2025-05-08T14:06:03.3141235+08:00",
    "metadataStatus": "Customize",
    "functionPageId": "08dd8df6-69cd-43d9-81c9-6f60b23b0e7e",
    "name": "08dd8df6-69cd-43bb-87b0-23eecc962c39",
    "application": "8001",
    "functionGUID": "08dd8c49-dab3-4283-8056-75e66abccbe1",
    "templateId": "2c63e14e-ff7e-4e0b-ae15-fefb8da34213",
    "autoTitle": false,
    "isDefault": false,
    "pageHandlerPluginTypeId": "00000000-0000-0000-0000-000000000000",
    "pageHandlerExPluginTypeId": "00000000-0000-0000-0000-000000000000",
    "entityId": "00000000-0000-0000-0000-000000000000",
    "title": "资产租赁信息填报列表",
    "pageName": "资产租赁信息填报列表",
    "titleEn": "x_List_0638",
    "titleSuffix": "列表页面",
    "url": "/std/x_80011901/08dd8df6-69cd-43bb-87b0-23eecc962c39",
    "pageType": "0",
    "functionCode": "x_80011901",
    "loadDefaultResource": false,
    "description": "资产租赁信息填报列表",
    "isAllowEdit": true,
    "exposed": false,
    "enablePageRouting": false,
    "editMode": "AllowAll",
    "isRevisedId": "1",
    "openness": "none",
    "metaDataExtendType": "None",
    "inheritFrom": "00000000-0000-0000-0000-000000000000",
    "enableInherited": false,
    "page": {
      "events": [
          {
            "name": "window.load",
            "enabled": false,
            "metadataStatus": "Product"
          },
          {
            "name": "document.ready",
            "enabled": false,
            "metadataStatus": "Product"
          },
          {
            "name": "control.ready",
            "functionName": "Mysoft.asset.Mx_80011901.x_List_0638",
            "enabled": true,
            "metadataStatus": "Product"
          }
        ]
    },
    "pageLayout": {
      "pageLayoutCategory": "OneColumn",
      "layoutType": "0",
      "pageMargin": "0",
      "pageHeightSetting": "Repeat",
      "cells": [{
          "id": "08dd8df6-69cd-457a-8146-3915d57ca2c9",
          "width": "100%",
          "height": "100%",
          "isHidden": false,
          "w": "0",
          "h": "0",
          "x": "0",
          "y": "0",
          "rowIndex": "0",
          "extensible": false,
          "direction": "column",
          "cells":  [{
              "id": "08dd8df6-69cd-45ac-847b-9d340ab9d7f3",
              "width": "100%",
              "height": "100%",
              "isHidden": false,
              "w": "0",
              "h": "0",
              "x": "0",
              "y": "0",
              "rowIndex": "0",
              "extensible": false,
              "direction": "column",
              "control": {
                "createdOn": "0001-01-01T00:00:00",
                "modifiedOn": "0001-01-01T00:00:00",
                "metadataStatus": "Customize",
                "id": "x_appGrid",
                "type": "Mysoft.Map6.Modeling.Controls.AppGrid",
                "metadataId": "08dd8df6-69cd-497a-8da0-2cc7f4816c2b",
                "templateId": "CFD8041A-0A92-4815-AB27-ECF447877C48",
                "entityName": "主实体",
                "reserved": "0",
                "autoHeight": "1"
              }
            }]
      }]
    }
  }
